{
  "id": 3014054307,
  "id_str": "3014054307",
  "name": "jsunderhood",
  "screen_name": "jsunderhood",
  "location": "Ростов-на-Дону",
  "profile_location": null,
  "description": "Влад Шилов (@omgovich) — Frontend-разработчик, охотник на резиновых уточек",
  "url": "https://t.co/N4CV81kFpt",
  "entities": {
    "url": {
      "urls": [
        {
          "url": "https://t.co/N4CV81kFpt",
          "expanded_url": "https://github.com/omgovich",
          "display_url": "github.com/omgovich",
          "indices": [
            0,
            23
          ]
        }
      ]
    },
    "description": {
      "urls": []
    }
  },
  "protected": false,
  "followers_count": 8545,
  "friends_count": 575,
  "listed_count": 232,
  "created_at": "Tue Feb 03 07:35:41 +0000 2015",
  "favourites_count": 6087,
  "utc_offset": null,
  "time_zone": null,
  "geo_enabled": false,
  "verified": false,
  "statuses_count": 41893,
  "lang": null,
  "status": {
    "created_at": "Wed Oct 21 22:06:50 +0000 2020",
    "id": 1319037453836177400,
    "id_str": "1319037453836177409",
    "text": "@lzakirov @gladkih_m @toivonens По-моему такой гифкой несколько проблем решали, но пока вспомнил, только то, что чи… https://t.co/Gq05Sazquy",
    "truncated": true,
    "entities": {
      "hashtags": [],
      "symbols": [],
      "user_mentions": [
        {
          "screen_name": "lzakirov",
          "name": "Lenar Zakirov❌",
          "id": 35164236,
          "id_str": "35164236",
          "indices": [
            0,
            9
          ]
        },
        {
          "screen_name": "gladkih_m",
          "name": "Maxim Gladkih",
          "id": 16400433,
          "id_str": "16400433",
          "indices": [
            10,
            20
          ]
        },
        {
          "screen_name": "toivonens",
          "name": "var ya; // ru 🇫🇮",
          "id": 215559242,
          "id_str": "215559242",
          "indices": [
            21,
            31
          ]
        }
      ],
      "urls": [
        {
          "url": "https://t.co/Gq05Sazquy",
          "expanded_url": "https://twitter.com/i/web/status/1319037453836177409",
          "display_url": "twitter.com/i/web/status/1…",
          "indices": [
            117,
            140
          ]
        }
      ]
    },
    "source": "<a href=\"https://mobile.twitter.com\" rel=\"nofollow\">Twitter Web App</a>",
    "in_reply_to_status_id": 1319009056053465000,
    "in_reply_to_status_id_str": "1319009056053465088",
    "in_reply_to_user_id": 35164236,
    "in_reply_to_user_id_str": "35164236",
    "in_reply_to_screen_name": "lzakirov",
    "geo": null,
    "coordinates": null,
    "place": null,
    "contributors": null,
    "is_quote_status": false,
    "retweet_count": 0,
    "favorite_count": 0,
    "favorited": false,
    "retweeted": false,
    "lang": "ru"
  },
  "contributors_enabled": false,
  "is_translator": false,
  "is_translation_enabled": false,
  "profile_background_color": "000000",
  "profile_background_image_url": "http://abs.twimg.com/images/themes/theme18/bg.gif",
  "profile_background_image_url_https": "https://abs.twimg.com/images/themes/theme18/bg.gif",
  "profile_background_tile": false,
  "profile_image_url": "http://pbs.twimg.com/profile_images/1318110455802531840/P0B5nEgl_normal.jpg",
  "profile_image_url_https": "https://pbs.twimg.com/profile_images/1318110455802531840/P0B5nEgl_normal.jpg",
  "profile_banner_url": "https://pbs.twimg.com/profile_banners/3014054307/1603096998",
  "profile_link_color": "1B95E0",
  "profile_sidebar_border_color": "000000",
  "profile_sidebar_fill_color": "000000",
  "profile_text_color": "000000",
  "profile_use_background_image": false,
  "has_extended_profile": false,
  "default_profile": false,
  "default_profile_image": false,
  "following": true,
  "follow_request_sent": false,
  "notifications": false,
  "translator_type": "none"
}
